py_tools/__init__.py
py_tools/version.py
py_tools/cli/__init__.py
py_tools/cli/main.py
my_py_tools-0.1.15.dist-info/AUTHORS.rst
my_py_tools-0.1.15.dist-info/LICENSE.txt
my_py_tools-0.1.15.dist-info/METADATA
my_py_tools-0.1.15.dist-info/WHEEL
my_py_tools-0.1.15.dist-info/entry_points.txt
my_py_tools-0.1.15.dist-info/top_level.txt
my_py_tools-0.1.15.dist-info/RECORD
