Metadata-Version: 2.1
Name: my-py-tools
Version: 0.1.15
Summary: py_tools is a modern python library
Home-page: https://github.com/DerThorsten/py_tools
Author: Thorsten Beier
Author-email: derthorstenbeier@gmail.com
License: UNKNOWN
Keywords: py_tools
Platform: UNKNOWN
Classifier: Development Status :: 2 - Pre-Alpha
Classifier: Intended Audience :: Developers
Classifier: Natural Language :: English
Classifier: Programming Language :: Python :: 3.6
Classifier: Programming Language :: Python :: 3.7
Classifier: Programming Language :: Python :: 3.8
Requires-Dist: click (>=6.0)
